Workbook

Sheet Instructions
A1: PB Copilot — Personal Financial Planner
B3: SYNTHETIC SAMPLE DATA — every figure and name below is fictional, for demo only.
A5: 1 | B5: "Cash Flow & Net Worth" — document income, expenses, assets, liabilities, and current insurance.
A6: 2 | B6: "Retirement" — estimates the corpus you need and the monthly investment to get there.
A7: 3 | B7: "Goals" — short/medium/long-term goals (education, house, car) with future value and monthly SIP needed.
A8: 4 | B8: "HLV" — Human Life Value: how much life insurance you actually need.
A9: 5 | B9: "Summary" — one-glance view: emergency fund, insurance gaps, and per-goal monthly investment.
B11: Educational guidance only — not a substitute for a licensed financial advisor.

Sheet CashFlow_NetWorth
A1: Cash Flow & Net Worth
A2: Yellow cells = your inputs. Others are formulas.
A4: Monthly Income | B4: INR/month
A5: Net Salary | B5: 150000
A6: Spouse Net Income | B6: 60000
A7: Rental Income (post tax) | B7: 0
A8: Other Income | B8: 5000
A9: Total Income | B9: =SUM(B5:B8) -> 215000
A11: Monthly Expenses | B11: INR/month
A12: Home Loan / Rent EMI | B12: 34000
A13: Food & Groceries | B13: 22000
A14: Utilities & Bills | B14: 9000
A15: Transport & Fuel | B15: 7000
A16: Children School Fees | B16: 18000
A17: Medical | B17: 4000
A18: Insurance Premiums | B18: 6000
A19: Subscriptions & Lifestyle | B19: 5000
A20: Discretionary | B20: 12000
A21: Total Expenses | B21: =SUM(B12:B20) -> 117000
A22: Net Monthly Savings | B22: =B9-B21 -> 98000
A24: Assets (current value) | B24: INR | D24: Liabilities (outstanding) | E24: INR
A25: Self-occupied Property | B25: 9000000 | D25: Home Loan | E25: 4000000
A26: EPF / PPF Balance | B26: 800000 | D26: Car Loan | E26: 0
A27: Fixed Deposits | B27: 300000 | D27: Credit Card | E27: 80000
A28: Equity Mutual Funds | B28: 600000 | D28: Personal Loan | E28: 0
A29: Debt Mutual Funds | B29: 200000 | D29: Other Loan | E29: 0
A30: Stocks | B30: 250000
A31: Gold (all forms) | B31: 400000
A32: NPS | B32: 150000
A33: Savings Account | B33: 180000
A34: Total Assets | B34: =SUM(B25:B33) -> 11880000 | D34: Total Liabilities | E34: =SUM(E25:E29) -> 4080000
A35: Net Worth | B35: =B34-E34 -> 7800000
A37: Current Insurance | B37: Cover (INR)
A38: Life Insurance (total) | B38: 2500000
A39: Health Insurance (total) | B39: 500000

Sheet Retirement
A1: Retirement Planner
A3: Current Age | B3: 36
A4: Retirement Age | B4: 58
A5: Life Expectancy (plan till) | B5: 85
A6: Current Monthly Expenses (post-retirement) | B6: 80000
A7: Inflation | B7: 0.06
A8: Return on Investment (pre-retirement) | B8: 0.1
A9: Return post-retirement | B9: 0.075
A10: Amount Already Invested for Retirement | B10: 500000
A12: Years to Retirement | B12: =B4-B3 -> 22
A13: Monthly Expense at Retirement (inflated) | B13: =B6*(1+B7)^B12 -> 288282.99
A14: Annual Expense at Retirement | B14: =B13*12 -> 3459395.9
A15: Real Return post-retirement | B15: =(1+B9)/(1+B7)-1 -> 0.014150943
A16: Retirement Years | B16: =B5-B4 -> 27
A17: Corpus Required at Retirement | B17: =B14*(1-(1+B15)^(-B16))/B15 -> 77183715
A18: Future Value of Current Investment | B18: =B10*(1+B8)^B12 -> 4070137.5
A19: Net Corpus Still Needed | B19: =MAX(B17-B18,0) -> 73113578
A20: Monthly SIP Needed for Retirement | B20: =B19*(B8/12)/((1+B8/12)^(B12*12)-1) -> 76705.402

Sheet Goals
A1: Financial Goals
A3: Goal | B3: Current Cost (INR) | C3: Years | D3: Inflation | E3: Future Value | F3: Monthly SIP Needed
A4: Child 1 — Undergraduate | B4: 5000000 | C4: 12 | D4: 0.08 | E4: =B4*(1+D4)^C4 -> 12590851 | F4: =E4*(0.11/12)/((1+0.11/12)^(C4*12)-1) -> 42417.139
A5: Child 1 — Marriage | B5: 3000000 | C5: 24 | D5: 0.06 | E5: =B5*(1+D5)^C5 -> 12146804 | F5: =E5*(0.11/12)/((1+0.11/12)^(C5*12)-1) -> 8667.9477
A6: Child 2 — Undergraduate | B6: 5000000 | C6: 15 | D6: 0.08 | E6: =B6*(1+D6)^C6 -> 15860846 | F6: =E6*(0.11/12)/((1+0.11/12)^(C6*12)-1) -> 34882.8
A7: House Down Payment | B7: 3500000 | C7: 5 | D7: 0.07 | E7: =B7*(1+D7)^C7 -> 4908931.1 | F7: =E7*(0.11/12)/((1+0.11/12)^(C7*12)-1) -> 61733.521
A8: Car Upgrade | B8: 1200000 | C8: 4 | D8: 0.05 | E8: =B8*(1+D8)^C8 -> 1458607.5 | F8: =E8*(0.11/12)/((1+0.11/12)^(C8*12)-1) -> 24327.904
A9: Family Vacation Fund | B9: 400000 | C9: 2 | D9: 0.05 | E9: =B9*(1+D9)^C9 -> 441000 | F9: =E9*(0.11/12)/((1+0.11/12)^(C9*12)-1) -> 16511.557
A10: TOTAL Monthly SIP for Goals | F10: =SUM(F4:F9) -> 188540.87

Sheet HLV
A1: Human Life Value (Life Insurance Needed)
A3: Annual Income to Replace | B3: 1800000
A4: Years to Provide For | B4: 20
A5: Inflation | B5: 0.06
A6: Return on Investment | B6: 0.09
A7: Outstanding Loans | B7: =CashFlow_NetWorth!E34 -> 4080000
A8: Total Goal Corpus (from Goals FV) | B8: =SUM(Goals!E4:E9) -> 47407039
A9: Current Investments | B9: =SUM(CashFlow_NetWorth!B26:B33) -> 2880000
A10: Current Life Insurance | B10: =CashFlow_NetWorth!B38 -> 2500000
A12: Real Return | B12: =(1+B6)/(1+B5)-1 -> 0.028301887
A13: Income Replacement Corpus | B13: =B3*(1-(1+B12)^(-B4))/B12 -> 27204771
A14: Total Insurance Required | B14: =B13+B7+B8-B9 -> 75811809
A15: Additional Cover Needed | B15: =MAX(B14-B10,0) -> 73311809

Sheet Summary
A1: Financial Plan — Summary
A3: Net Monthly Savings | B3: =CashFlow_NetWorth!B22 -> 98000
A4: Net Worth | B4: =CashFlow_NetWorth!B35 -> 7800000
A5: Emergency Fund Needed (6 months expenses) | B5: =CashFlow_NetWorth!B21*6 -> 702000
A6: Retirement Corpus Required | B6: =Retirement!B17 -> 77183715
A7: Monthly SIP for Retirement | B7: =Retirement!B20 -> 76705.402
A8: Total Monthly SIP for Goals | B8: =Goals!F10 -> 188540.87
A9: Additional Life Insurance Needed | B9: =HLV!B15 -> 73311809
A10: Total Monthly Investment Required | B10: =Retirement!B20+Goals!F10 -> 265246.27
A12: Educational guidance only — not licensed financial advice.
